reactpy_table/__init__.py
reactpy_table/core/__init__.py
reactpy_table/core/feature_factories.py
reactpy_table/core/options.py
reactpy_table/core/reactpy_table.py
reactpy_table/core/reactpy_table_init.py
reactpy_table/features/__init__.py
reactpy_table/features/column_sort.py
reactpy_table/features/null_updater.py
reactpy_table/features/paginator.py
reactpy_table/features/row_model.py
reactpy_table/features/table_search.py
reactpy_table/types/__init__.py
reactpy_table/types/abstract_column_sort.py
reactpy_table/types/abstract_paginator.py
reactpy_table/types/abstract_row_model.py
reactpy_table/types/abstract_table.py
reactpy_table/types/abstract_table_search.py
reactpy_table/types/feature.py
reactpy_table/types/feature_control.py
reactpy_table/types/paginator_state.py
reactpy_table/types/search_state.py
reactpy_table/types/sort_state.py
reactpy_table/types/table.py
reactpy_table/types/table_data.py
reactpy_table/types/table_state.py
reactpy_table/utils/__init__.py
reactpy_table/utils/memo.py
reactpy_table-0.0.15.dist-info/LICENSE
reactpy_table-0.0.15.dist-info/METADATA
reactpy_table-0.0.15.dist-info/WHEEL
reactpy_table-0.0.15.dist-info/RECORD
