Metadata-Version: 2.1
Name: reactpy-table
Version: 0.0.15
Summary: Headless UI for building powerful tables
Home-page: https://github.com/stevej2608/reactpy-table/blob/master/README.md
License: MIT
Author: Steve Jones
Author-email: jonesst2608@gmail.com
Requires-Python: >=3.11,<4.0
Classifier: License :: OSI Approved :: MIT License
Classifier: Programming Language :: Python :: 3
Classifier: Programming Language :: Python :: 3.11
Classifier: Programming Language :: Python :: 3.12
Classifier: Programming Language :: Python :: 3.13
Requires-Dist: reactpy (>=1.1.0,<2.0.0)
Project-URL: Repository, https://github.com/stevej2608/reactpy-table
